easygui/__init__.py
easygui/easygui.py
easygui/python_and_check_logo.gif
easygui/python_and_check_logo.jpg
easygui/python_and_check_logo.png
easygui/zzzzz.gif
easygui/boxes/__init__.py
easygui/boxes/about.py
easygui/boxes/base_boxes.py
easygui/boxes/button_box.py
easygui/boxes/choice_box.py
easygui/boxes/demo.py
easygui/boxes/derived_boxes.py
easygui/boxes/diropen_box.py
easygui/boxes/egstore.py
easygui/boxes/fileboxsetup.py
easygui/boxes/fileopen_box.py
easygui/boxes/filesave_box.py
easygui/boxes/fillable_box.py
easygui/boxes/global_state.py
easygui/boxes/multi_fillable_box.py
easygui/boxes/text_box.py
easygui/boxes/utils.py
easygui-0.98.1.dist-info/DESCRIPTION.rst
easygui-0.98.1.dist-info/METADATA
easygui-0.98.1.dist-info/RECORD
easygui-0.98.1.dist-info/WHEEL
easygui-0.98.1.dist-info/metadata.json
easygui-0.98.1.dist-info/top_level.txt
