Metadata-Version: 1.1
Name: easygui
Version: 0.98.1
Summary: EasyGUI is a module for very simple, very easy GUI programming in Python.  EasyGUI is different from other GUI generators in that EasyGUI is NOT event-driven.  Instead, all GUI interactions are invoked by simple function calls.
Home-page: https://github.com/robertlugg/easygui
Author: easygui developers and Stephen Ferg
Author-email: robert.lugg@gmail.com
License: BSD
Keywords: gui linux windows graphical user interface
Platform: UNKNOWN
Classifier: Intended Audience :: Developers
Classifier: Intended Audience :: Education
Classifier: License :: OSI Approved :: BSD License
Classifier: Programming Language :: Python
Classifier: Programming Language :: Python :: 2
Classifier: Programming Language :: Python :: 2.6
Classifier: Programming Language :: Python :: 2.7
Classifier: Programming Language :: Python :: 3
Classifier: Programming Language :: Python :: 3.3
Classifier: Programming Language :: Python :: 3.4
Classifier: Programming Language :: Python :: 3.4
Classifier: Topic :: Software Development :: User Interfaces
